bubot_webserver/__init__.py
bubot_webserver/buject/OcfDevice/subtype/OcfCloudTcpServer/OcfCloudTcpServer.json
bubot_webserver/buject/OcfDevice/subtype/OcfCloudTcpServer/OcfCloudTcpServer.py
bubot_webserver/buject/OcfDevice/subtype/OcfCloudTcpServer/OicRd.py
bubot_webserver/buject/OcfDevice/subtype/OcfCloudTcpServer/OicSecAccount.py
bubot_webserver/buject/OcfDevice/subtype/OcfCloudTcpServer/OicSecSession.py
bubot_webserver/buject/OcfDevice/subtype/OcfCloudTcpServer/__init__.py
bubot_webserver/buject/OcfDevice/subtype/WebServer/ApiHelper.py
bubot_webserver/buject/OcfDevice/subtype/WebServer/FormHandler.py
bubot_webserver/buject/OcfDevice/subtype/WebServer/HttpHandler.py
bubot_webserver/buject/OcfDevice/subtype/WebServer/SchemaHandler.py
bubot_webserver/buject/OcfDevice/subtype/WebServer/SessionStorageApp.py
bubot_webserver/buject/OcfDevice/subtype/WebServer/SessionStorageMongo.py
bubot_webserver/buject/OcfDevice/subtype/WebServer/WebServer.json
bubot_webserver/buject/OcfDevice/subtype/WebServer/WebServer.py
bubot_webserver/buject/OcfDevice/subtype/WebServer/WsHandler.md
bubot_webserver/buject/OcfDevice/subtype/WebServer/WsHandler.py
bubot_webserver/buject/OcfDevice/subtype/WebServer/__init__.py
bubot_webserver/buject/OcfDevice/subtype/WebServer/APImixin/Device.py
bubot_webserver/buject/OcfDevice/subtype/WebServer/APImixin/Driver.py
bubot_webserver/buject/OcfDevice/subtype/WebServer/APImixin/Resource.py
bubot_webserver/buject/OcfDevice/subtype/WebServer/APImixin/Schema.py
bubot_webserver/buject/OcfDevice/subtype/WebServer/APImixin/Store.py
bubot_webserver/buject/OcfDevice/subtype/WebServer/APImixin/__init__.py
bubot_webserver/buject/OcfDevice/subtype/WebServer/i18n/en.json
bubot_webserver/buject/OcfDevice/subtype/WebServer/i18n/ru.json
bubot_webserver-4.1.2.dist-info/licenses/LICENSE
bubot_webserver-4.1.2.dist-info/METADATA
bubot_webserver-4.1.2.dist-info/WHEEL
bubot_webserver-4.1.2.dist-info/top_level.txt
bubot_webserver-4.1.2.dist-info/RECORD
