Metadata-Version: 2.4
Name: bubot_webserver
Version: 4.1.2
Summary: Web server for Bubot
Home-page: https://github.com/businka/Bubot_WebServer
Author: Razgovorov Mikhail
Author-email: 1338833@gmail.com
Classifier: Programming Language :: Python :: 3
Classifier: License :: OSI Approved :: MIT License
Classifier: Operating System :: OS Independent
Classifier: Development Status :: 3 - Alpha
Classifier: Framework :: AsyncIO
Requires-Python: >=3.7
License-File: LICENSE
Requires-Dist: motor>=3
Requires-Dist: redis>4.2
Requires-Dist: aiohttp==3.9.3
Requires-Dist: aiohttp-session>=2.9
Requires-Dist: bubot_core<4.2,>=4.1.0
Dynamic: author
Dynamic: author-email
Dynamic: classifier
Dynamic: description
Dynamic: description-content-type
Dynamic: home-page
Dynamic: license-file
Dynamic: requires-dist
Dynamic: requires-python
Dynamic: summary
